boldigger3/__init__.py
boldigger3/__main__.py
boldigger3/add_metadata.py
boldigger3/exceptions.py
boldigger3/id_engine.py
boldigger3/metadata_download.py
boldigger3/select_top_hit.py
boldigger3-2.2.0.dist-info/licenses/LICENSE
boldigger3-2.2.0.dist-info/METADATA
boldigger3-2.2.0.dist-info/WHEEL
boldigger3-2.2.0.dist-info/entry_points.txt
boldigger3-2.2.0.dist-info/top_level.txt
boldigger3-2.2.0.dist-info/RECORD
