Metadata-Version: 2.4
Name: boldigger3
Version: 2.2.0
Summary: A python package to query different databases of boldsystems.org v5!
Home-page: https://github.com/DominikBuchner/BOLDigger3
Author: Dominik Buchner
Author-email: dominik.buchner@uni-due.de
License: MIT
Classifier: Programming Language :: Python :: 3
Classifier: License :: OSI Approved :: MIT License
Classifier: Operating System :: OS Independent
Requires-Python: >=3.11
License-File: LICENSE
Requires-Dist: Bio>=1.8.0
Requires-Dist: biopython>=1.85
Requires-Dist: dask>=2025.3.0
Requires-Dist: duckdb>=1.3.2
Requires-Dist: luddite>=1.0.4
Requires-Dist: more_itertools>=10.5.0
Requires-Dist: numpy>=2.0.0
Requires-Dist: pandas>=2.2.3
Requires-Dist: python_dateutil>=2.9.0
Requires-Dist: Requests>=2.32.3
Requires-Dist: requests_html>=0.10.0
Requires-Dist: setuptools>=65.5.0
Requires-Dist: tqdm>=4.66.4
Requires-Dist: urllib3>=1.26.14
Requires-Dist: tables>=3.9.2
Requires-Dist: openpyxl>=3.1.1
Requires-Dist: pyarrow>=11.0.0
Requires-Dist: xlsxwriter>=3.0.5
Dynamic: author
Dynamic: author-email
Dynamic: classifier
Dynamic: description
Dynamic: description-content-type
Dynamic: home-page
Dynamic: license
Dynamic: license-file
Dynamic: requires-dist
Dynamic: requires-python
Dynamic: summary
